certy/__init__.py
certy/certificate_revocation_list.py
certy/credential.py
certy-0.2.2.dist-info/licenses/LICENSE
certy-0.2.2.dist-info/WHEEL
certy-0.2.2.dist-info/METADATA
certy-0.2.2.dist-info/RECORD
