Metadata-Version: 2.4
Name: certy
Version: 0.2.2
Summary: Certy is a simple X509 certificate generator for unit and integration tests.
Keywords: testing,certificates,x509,pki
Author-email: Tero Saarni <tero.saarni@gmail.com>
Requires-Python: >=3.9
Classifier: License :: OSI Approved :: Apache Software License
License-File: LICENSE
Requires-Dist: cryptography>=42.0.0
Project-URL: Documentation, https://tsaarni.github.io/python-certy/
Project-URL: Source, https://github.com/tsaarni/python-certy
